odoo/addons/l10n_ro_stock_picking_valued_report/README.rst
odoo/addons/l10n_ro_stock_picking_valued_report/__init__.py
odoo/addons/l10n_ro_stock_picking_valued_report/__manifest__.py
odoo/addons/l10n_ro_stock_picking_valued_report/i18n/l10n_ro_stock_picking_valued_report.pot
odoo/addons/l10n_ro_stock_picking_valued_report/i18n/ro.po
odoo/addons/l10n_ro_stock_picking_valued_report/models/__init__.py
odoo/addons/l10n_ro_stock_picking_valued_report/models/stock_move_line.py
odoo/addons/l10n_ro_stock_picking_valued_report/models/stock_picking.py
odoo/addons/l10n_ro_stock_picking_valued_report/readme/CONTRIBUTORS.md
odoo/addons/l10n_ro_stock_picking_valued_report/readme/DESCRIPTION.md
odoo/addons/l10n_ro_stock_picking_valued_report/readme/INSTALL.md
odoo/addons/l10n_ro_stock_picking_valued_report/report/stock_picking_report_valued.xml
odoo/addons/l10n_ro_stock_picking_valued_report/static/description/icon.png
odoo/addons/l10n_ro_stock_picking_valued_report/static/description/icon.svg
odoo/addons/l10n_ro_stock_picking_valued_report/static/description/index.html
odoo/addons/l10n_ro_stock_picking_valued_report/tests/__init__.py
odoo/addons/l10n_ro_stock_picking_valued_report/tests/common.py
odoo/addons/l10n_ro_stock_picking_valued_report/tests/test_ro_stock_avg.py
odoo/addons/l10n_ro_stock_picking_valued_report/tests/test_ro_stock_fifo.py
odoo/addons/l10n_ro_stock_picking_valued_report/tests/cases/test_cases_avg.csv
odoo/addons/l10n_ro_stock_picking_valued_report/tests/cases/test_cases_fifo.csv
odoo_addon_l10n_ro_stock_picking_valued_report-19.0.0.0.0.2.dist-info/METADATA
odoo_addon_l10n_ro_stock_picking_valued_report-19.0.0.0.0.2.dist-info/WHEEL
odoo_addon_l10n_ro_stock_picking_valued_report-19.0.0.0.0.2.dist-info/top_level.txt
odoo_addon_l10n_ro_stock_picking_valued_report-19.0.0.0.0.2.dist-info/RECORD
