Metadata-Version: 2.1
Name: odoo-addon-l10n_ro_stock_picking_valued_report
Version: 19.0.0.0.0.2
Requires-Dist: odoo-addon-l10n_ro_stock_account_landed_cost==19.0.*
Requires-Dist: odoo==19.0.*
Summary: Romania - Stock Picking Valued Report
Home-page: https://github.com/OCA/l10n-romania
License: AGPL-3
Author: NextERP Romania,Odoo Community Association (OCA)
Author-email: support@odoo-community.org
Classifier: Programming Language :: Python
Classifier: Framework :: Odoo
Classifier: Framework :: Odoo :: 19.0
Classifier: License :: OSI Approved :: GNU Affero General Public License v3
Classifier: Development Status :: 6 - Mature
